libcloudclodoru/__init__.py
libcloudclodoru-0.0.2.dist-info/LICENSE
libcloudclodoru-0.0.2.dist-info/METADATA
libcloudclodoru-0.0.2.dist-info/WHEEL
libcloudclodoru-0.0.2.dist-info/top_level.txt
libcloudclodoru-0.0.2.dist-info/RECORD
