Metadata-Version: 2.1
Name: libcloudclodoru
Version: 0.0.2
Summary: Libcloud driver for provdier clodo.ru
Home-page: https://github.com/thebits/libcloud-clodoru
Author: Sergey Mezentsev
Author-email: thebits@yandex.ru
License: UNLICENSE
Classifier: Intended Audience :: System Administrators
Classifier: Operating System :: OS Independent
Classifier: Programming Language :: Python :: 3
Classifier: Topic :: System :: Systems Administration
Requires-Python: >=3.6
License-File: LICENSE
Requires-Dist: apache-libcloud (>=3.0.0)
